susy_cross_section/__init__.py
susy_cross_section/base/__init__.py
susy_cross_section/base/info.py
susy_cross_section/base/table.py
susy_cross_section/config.py
susy_cross_section/data/lhc_susy_xs_wg/13TeVn1n2hino_deg_cteq.csv
susy_cross_section/data/lhc_susy_xs_wg/13TeVn1n2hino_deg_cteq.info
susy_cross_section/data/lhc_susy_xs_wg/13TeVn1n2hino_deg_envelope.csv
susy_cross_section/data/lhc_susy_xs_wg/13TeVn1n2hino_deg_envelope.info
susy_cross_section/data/lhc_susy_xs_wg/13TeVn1n2hino_deg_mstw.csv
susy_cross_section/data/lhc_susy_xs_wg/13TeVn1n2hino_deg_mstw.info
susy_cross_section/data/lhc_susy_xs_wg/13TeVn2x1hino_deg_cteq_m.csv
susy_cross_section/data/lhc_susy_xs_wg/13TeVn2x1hino_deg_cteq_m.info
susy_cross_section/data/lhc_susy_xs_wg/13TeVn2x1hino_deg_cteq_p.csv
susy_cross_section/data/lhc_susy_xs_wg/13TeVn2x1hino_deg_cteq_p.info
susy_cross_section/data/lhc_susy_xs_wg/13TeVn2x1hino_deg_cteq_pm.csv
susy_cross_section/data/lhc_susy_xs_wg/13TeVn2x1hino_deg_cteq_pm.info
susy_cross_section/data/lhc_susy_xs_wg/13TeVn2x1hino_deg_envelope_pm.csv
susy_cross_section/data/lhc_susy_xs_wg/13TeVn2x1hino_deg_envelope_pm.info
susy_cross_section/data/lhc_susy_xs_wg/13TeVn2x1hino_deg_mstw_m.csv
susy_cross_section/data/lhc_susy_xs_wg/13TeVn2x1hino_deg_mstw_m.info
susy_cross_section/data/lhc_susy_xs_wg/13TeVn2x1hino_deg_mstw_p.csv
susy_cross_section/data/lhc_susy_xs_wg/13TeVn2x1hino_deg_mstw_p.info
susy_cross_section/data/lhc_susy_xs_wg/13TeVn2x1hino_deg_mstw_pm.csv
susy_cross_section/data/lhc_susy_xs_wg/13TeVn2x1hino_deg_mstw_pm.info
susy_cross_section/data/lhc_susy_xs_wg/13TeVn2x1wino_cteq_m.csv
susy_cross_section/data/lhc_susy_xs_wg/13TeVn2x1wino_cteq_m.info
susy_cross_section/data/lhc_susy_xs_wg/13TeVn2x1wino_cteq_p.csv
susy_cross_section/data/lhc_susy_xs_wg/13TeVn2x1wino_cteq_p.info
susy_cross_section/data/lhc_susy_xs_wg/13TeVn2x1wino_cteq_pm.csv
susy_cross_section/data/lhc_susy_xs_wg/13TeVn2x1wino_cteq_pm.info
susy_cross_section/data/lhc_susy_xs_wg/13TeVn2x1wino_envelope_m.csv
susy_cross_section-0.2.3.dist-info/entry_points.txt
susy_cross_section-0.2.3.dist-info/LICENSE
susy_cross_section-0.2.3.dist-info/WHEEL
susy_cross_section-0.2.3.dist-info/METADATA
susy_cross_section-0.2.3.dist-info/RECORD
