Metadata-Version: 2.1
Name: susy-cross-section
Version: 0.2.3
Summary: A Python package for high-energy physics analysis to provide SUSY cross section data
Home-page: https://github.com/misho104/susy_cross_section
License: MIT
Author: Sho Iwamoto (Misho)
Author-email: webmaster@misho-web.com
Requires-Python: >=3.8,<3.11
Classifier: License :: OSI Approved :: MIT License
Classifier: Programming Language :: Python :: 3
Classifier: Programming Language :: Python :: 3.8
Classifier: Programming Language :: Python :: 3.9
Requires-Dist: click (>=8.0,<9.0)
Requires-Dist: colorama (>=0.4,<0.5)
Requires-Dist: coloredlogs (>=15.0,<16.0)
Requires-Dist: numpy (>=1.21,<2.0)
Requires-Dist: pandas (>=1.2,<2.0)
Requires-Dist: scipy (>=1.8,<2.0)
Project-URL: Repository, https://github.com/misho104/susy_cross_section
